webscrapehelper/__init__.py
webscrapehelper/session.py
webscrapehelper-0.1.0.dist-info/licenses/LICENSE
webscrapehelper-0.1.0.dist-info/METADATA
webscrapehelper-0.1.0.dist-info/WHEEL
webscrapehelper-0.1.0.dist-info/top_level.txt
webscrapehelper-0.1.0.dist-info/RECORD
